ddd_layer/DDD.py
ddd_layer/__init__.py
ddd_layer/ddd_test.py
ddd_layer-0.0.2.dist-info/LICENSE.txt
ddd_layer-0.0.2.dist-info/METADATA
ddd_layer-0.0.2.dist-info/WHEEL
ddd_layer-0.0.2.dist-info/top_level.txt
ddd_layer-0.0.2.dist-info/RECORD
