Metadata-Version: 2.1
Name: ddd_layer
Version: 0.0.2
Summary: this calculate symbolic determinants
Author-email: luisCorl <lui.corl.ing@hotmail.com>
Project-URL: Homepage, https://github.com/luisCorl/ddd_layer
Project-URL: Issues, https://github.com/luisCorl/ddd_layer
Classifier: Programming Language :: Python :: 3
Classifier: License :: OSI Approved :: GNU General Public License v3 (GPLv3)
Classifier: Operating System :: OS Independent
Requires-Python: >=3.4
License-File: LICENSE.txt
